spacy_detok/__init__.py
spacy_detok-0.6.0.dist-info/WHEEL
spacy_detok-0.6.0.dist-info/METADATA
spacy_detok-0.6.0.dist-info/RECORD
