Metadata-Version: 2.1
Name: spacy-detok
Version: 0.6.0
Summary: Invert spaCy detokenization
Author: melisa
Requires-Python: >=3.8,<4.0
Classifier: Programming Language :: Python :: 3
Classifier: Programming Language :: Python :: 3.8
Classifier: Programming Language :: Python :: 3.9
Requires-Dist: numpy (>=1.21.0,<2.0.0)
Requires-Dist: torch (>=1.9.0,<2.0.0)
Requires-Dist: tqdm (>=4.61.1,<5.0.0)
Requires-Dist: transformers (>=4.8.2,<5.0.0)
